tj_middle_server/__init__.py
tj_middle_server/manage.py
tj_middle_server/apps/__init__.py
tj_middle_server/apps/urls.py
tj_middle_server/apps/user/__init__.py
tj_middle_server/apps/user/admin.py
tj_middle_server/apps/user/apps.py
tj_middle_server/apps/user/filters.py
tj_middle_server/apps/user/models.py
tj_middle_server/apps/user/serializers.py
tj_middle_server/apps/user/tests.py
tj_middle_server/apps/user/views.py
tj_middle_server/apps/user/migrations/0001_initial.py
tj_middle_server/apps/user/migrations/__init__.py
tj_middle_server/apps/utils/__init__.py
tj_middle_server/apps/utils/pager.py
tj_middle_server/apps/utils/response.py
tj_middle_server/apps/utils/utils.py
tj_middle_server/apps/utils/yeahModalViewSet.py
tj_middle_server/extra_apps/__init__.py
tj_middle_server/tj_middle_server/__init__.py
tj_middle_server/tj_middle_server/asgi.py
tj_middle_server/tj_middle_server/settings.py
tj_middle_server/tj_middle_server/wsgi.py
smuport_tj_middle_server-1.0.1.dist-info/LICENSE
smuport_tj_middle_server-1.0.1.dist-info/METADATA
smuport_tj_middle_server-1.0.1.dist-info/WHEEL
smuport_tj_middle_server-1.0.1.dist-info/top_level.txt
smuport_tj_middle_server-1.0.1.dist-info/RECORD
